{"_meta":{"description":"This file contains a serialized version of schema entities for drift.","version":"1.2.0"},"options":{"store_date_time_values_as_text":false},"entities":[{"id":0,"references":[],"type":"table","data":{"name":"notes","was_declared_in_moor":false,"columns":[{"name":"id","getter_name":"id","moor_type":"int","nullable":false,"customConstraints":null,"defaultConstraints":"PRIMARY KEY AUTOINCREMENT","dialectAwareDefaultConstraints":{"sqlite":"PRIMARY KEY AUTOINCREMENT"},"default_dart":null,"default_client_dart":null,"dsl_features":["auto-increment"]},{"name":"title","getter_name":"title","moor_type":"string","nullable":false,"customConstraints":null,"default_dart":null,"default_client_dart":null,"dsl_features":[{"allowed-lengths":{"min":0,"max":128}}]},{"name":"content","getter_name":"content","moor_type":"string","nullable":false,"customConstraints":null,"default_dart":null,"default_client_dart":null,"dsl_features":[]},{"name":"created_at","getter_name":"createdAt","moor_type":"dateTime","nullable":true,"customConstraints":null,"default_dart":null,"default_client_dart":null,"dsl_features":[]}],"is_virtual":false,"without_rowid":false,"constraints":[]}},{"id":1,"references":[],"type":"table","data":{"name":"apps","was_declared_in_moor":false,"columns":[{"name":"id","getter_name":"id","moor_type":"int","nullable":false,"customConstraints":null,"defaultConstraints":"PRIMARY KEY AUTOINCREMENT","dialectAwareDefaultConstraints":{"sqlite":"PRIMARY KEY AUTOINCREMENT"},"default_dart":null,"default_client_dart":null,"dsl_features":["auto-increment"]},{"name":"title","getter_name":"title","moor_type":"string","nullable":false,"customConstraints":null,"default_dart":null,"default_client_dart":null,"dsl_features":[{"allowed-lengths":{"min":0,"max":128}}]},{"name":"package_name","getter_name":"packageName","moor_type":"string","nullable":false,"customConstraints":null,"defaultConstraints":"UNIQUE","dialectAwareDefaultConstraints":{"sqlite":"UNIQUE"},"default_dart":null,"default_client_dart":null,"dsl_features":["unknown"]}],"is_virtual":false,"without_rowid":false,"constraints":[]}},{"id":2,"references":[1],"type":"table","data":{"name":"home_apps","was_declared_in_moor":false,"columns":[{"name":"id","getter_name":"id","moor_type":"int","nullable":false,"customConstraints":null,"defaultConstraints":"PRIMARY KEY AUTOINCREMENT","dialectAwareDefaultConstraints":{"sqlite":"PRIMARY KEY AUTOINCREMENT"},"default_dart":null,"default_client_dart":null,"dsl_features":["auto-increment"]},{"name":"app_id","getter_name":"appId","moor_type":"int","nullable":false,"customConstraints":null,"defaultConstraints":"UNIQUE REFERENCES apps (id) ON DELETE CASCADE","dialectAwareDefaultConstraints":{"sqlite":"UNIQUE REFERENCES apps (id) ON DELETE CASCADE"},"default_dart":null,"default_client_dart":null,"dsl_features":["unknown","unknown"]},{"name":"position","getter_name":"position","moor_type":"int","nullable":false,"customConstraints":null,"default_dart":null,"default_client_dart":null,"dsl_features":[]}],"is_virtual":false,"without_rowid":false,"constraints":[]}}]}